README.rst
setup.py
toggl/__init__.py
toggl/api.py
toggl/config.py
toggl/main.py
toggl/schedule.py
toggl.egg-info/PKG-INFO
toggl.egg-info/SOURCES.txt
toggl.egg-info/dependency_links.txt
toggl.egg-info/entry_points.txt
toggl.egg-info/requires.txt
toggl.egg-info/top_level.txt