Metadata-Version: 1.0
Name: toggl
Version: 0.1.0
Summary: Automatically toggl your hours
Home-page: https://github.com/eodolphi/toggl
Author: Ernst Odolphi
Author-email: ernst.odolphi@gmail.com
License: MIT
Keywords: toggl automate
Platform: UNKNOWN
